irpy
