Metadata-Version: 1.1
Name: irpy
Version: 0.6.2
Summary: IRP for Python
Home-page: https://github.com/TApplencourt/IRPy
Author: Thomas Applencourt
Author-email: thomas.applencourt@irsamc.ups-tlse.fr
License: WTFPL
Download-URL: https://github.com/TApplencourt/IRPy/archive/master.tar.gz
Platform: UNKNOWN
